bionemo/webdatamodule/__init__.py
bionemo/webdatamodule/datamodule.py
bionemo/webdatamodule/utils.py
bionemo_webdatamodule-1.0.0.dist-info/licenses/LICENSE
bionemo_webdatamodule-1.0.0.dist-info/METADATA
bionemo_webdatamodule-1.0.0.dist-info/WHEEL
bionemo_webdatamodule-1.0.0.dist-info/top_level.txt
bionemo_webdatamodule-1.0.0.dist-info/RECORD
