Metadata-Version: 2.4
Name: bionemo-webdatamodule
Version: 1.0.0
Summary: PyTorch Lightning Data Module for WebDataset files.
Author-email: BioNeMo Team <bionemofeedback@nvidia.com>
License: 
Requires-Python: >=3.10
License-File: LICENSE
Requires-Dist: bionemo-core
Requires-Dist: webdataset==0.2.96
Dynamic: license-file
